<?xml version="1.0" encoding="utf-8"?>
<Defs>
  <ThingDef ParentName="AnimalThingBase">
    <defName>Mystogen</defName>
    <label>mystogen</label>
    <description>The most intelligent of the greater drakes, It often travels from place to place in order to locate it's prey. It can sense when someone is nearby by using it's psychic abilities and can stun it's prey with it. (Giddy up, +25% speed when ridden)</description>
    <statBases>
      <MoveSpeed>6.5</MoveSpeed>
      <MarketValue>5000</MarketValue>
      <ComfyTemperatureMin>-50</ComfyTemperatureMin>
      <ComfyTemperatureMax>75</ComfyTemperatureMax>
      <MeatAmount>65</MeatAmount>
      <LeatherAmount>35</LeatherAmount>
      <CarryingCapacity>75</CarryingCapacity>
      <ArmorRating_Sharp>0.60</ArmorRating_Sharp>
      <ArmorRating_Blunt>0.75</ArmorRating_Blunt>
      <ArmorRating_Heat>0.50</ArmorRating_Heat>
    </statBases>
    <tools>
      <li>
        <label>left claw</label>
        <capacities>
          <li>Scratch</li>
        </capacities>
        <power>25</power>
        <cooldownTime>1</cooldownTime>
        <linkedBodyPartsGroup>FrontLeftPaw</linkedBodyPartsGroup>
        <surpriseAttack>
          <extraMeleeDamages>
            <li>
              <def>Stun</def>
              <amount>5</amount>
            </li>
          </extraMeleeDamages>
        </surpriseAttack>
      </li>
      <li>
        <label>right claw</label>
        <capacities>
          <li>Scratch</li>
        </capacities>
        <power>25</power>
        <cooldownTime>1</cooldownTime>
        <linkedBodyPartsGroup>FrontLeftPaw</linkedBodyPartsGroup>
        <surpriseAttack>
          <extraMeleeDamages>
            <li>
              <def>Stun</def>
              <amount>5</amount>
            </li>
          </extraMeleeDamages>
        </surpriseAttack>
      </li>
      <li>
        <label>head</label>
        <capacities>
          <li>Blunt</li>
        </capacities>
        <power>26</power>
        <cooldownTime>1.5</cooldownTime>
        <linkedBodyPartsGroup>HeadAttackTool</linkedBodyPartsGroup>
        <ensureLinkedBodyPartsGroupAlwaysUsable>true</ensureLinkedBodyPartsGroupAlwaysUsable>
        <chanceFactor>0.5</chanceFactor>
        <surpriseAttack>
          <extraMeleeDamages>
            <li>
              <def>Stun</def>
              <amount>14</amount>
            </li>
          </extraMeleeDamages>
        </surpriseAttack>
      </li>
      <li>
        <capacities>
          <li>Bite</li>
        </capacities>
        <power>22</power>
        <cooldownTime>1</cooldownTime>
        <linkedBodyPartsGroup>Teeth</linkedBodyPartsGroup>
        <chanceFactor>0.7</chanceFactor>
      </li>
    </tools>
    <race>
      <body>QuadrupedAnimalWithPawsAndTail</body>
      <packAnimal>true</packAnimal>
      <predator>true</predator>
      <maxPreyBodySize>4.5</maxPreyBodySize>
      <baseHungerRate>0.3</baseHungerRate>
      <baseBodySize>5</baseBodySize>
      <baseHealthScale>6</baseHealthScale>
      <foodType>CarnivoreAnimal, OvivoreAnimal</foodType>
      <leatherDef>Leather_Mystogen</leatherDef>
      <gestationPeriodDays>35</gestationPeriodDays>
      <wildness>0.80</wildness>
      <trainability>Advanced</trainability>
      <nuzzleMtbHours>60</nuzzleMtbHours>
      <lifeExpectancy>400</lifeExpectancy>
      <manhunterOnTameFailChance>0.10</manhunterOnTameFailChance>
      <manhunterOnDamageChance>0.50</manhunterOnDamageChance>
      <litterSizeCurve>
        <points>
          <li>(0.5, 0)</li>
          <li>(1, 1)</li>
          <li>(1.3, 1)</li>
          <li>(2.0, 0)</li>
        </points>
      </litterSizeCurve>
      <lifeStageAges>
        <li>
          <def>AnimalBaby</def>
          <minAge>0</minAge>
        </li>
        <li>
          <def>AnimalJuvenile</def>
          <minAge>2.0</minAge>
        </li>
        <li>
          <def>AnimalAdult</def>
          <minAge>5.0</minAge>
          <soundCall>Mystogen_Call</soundCall>
          <soundAngry>Mystogen_Angry</soundAngry>
          <soundWounded>Mystogen_Hurt</soundWounded>
          <soundDeath>Mystogen_Death</soundDeath>
        </li>
      </lifeStageAges>
      <soundMeleeHitPawn>Pawn_Melee_BigBash_HitPawn</soundMeleeHitPawn>
      <soundMeleeHitBuilding>Pawn_Melee_BigBash_HitBuilding</soundMeleeHitBuilding>
      <soundMeleeMiss>Pawn_Melee_BigBash_Miss</soundMeleeMiss>
    </race>
    <tradeTags>
      <li>AnimalExotic</li>
    </tradeTags>
  </ThingDef>
  <PawnKindDef ParentName="AnimalKindBase">
    <defName>Mystogen</defName>
    <label>mystogen</label>
    <race>Mystogen</race>
    <combatPower>450</combatPower>
    <ecoSystemWeight>0.80</ecoSystemWeight>
    <lifeStages>
      <li>
        <bodyGraphicData>
          <texPath>Things/Nexomon/Mystogen/Mystogen</texPath>
          <drawSize>4.5</drawSize>
          <shadowData>
            <volume>(0.4, 0.3, 0.3)</volume>
            <offset>(0,0,-0.2)</offset>
          </shadowData>
        </bodyGraphicData>
        <dessicatedBodyGraphicData>
          <texPath>Things/Nexomon/Voltaic/Dessicated_Voltaic</texPath>
          <drawSize>4.5</drawSize>
        </dessicatedBodyGraphicData>
      </li>
      <li>
        <bodyGraphicData>
          <texPath>Things/Nexomon/Mystogen/Mystogen</texPath>
          <drawSize>4.5</drawSize>
          <shadowData>
            <volume>(0.6, 0.45, 0.45)</volume>
            <offset>(0,0,-0.25)</offset>
          </shadowData>
        </bodyGraphicData>
        <dessicatedBodyGraphicData>
          <texPath>Things/Nexomon/Mystogen/Dessicated_Mystogen</texPath>
          <drawSize>4.5</drawSize>
        </dessicatedBodyGraphicData>
      </li>
      <li>
        <bodyGraphicData>
          <texPath>Things/Nexomon/Mystogen/Mystogen</texPath>
          <drawSize>4.5</drawSize>
          <shadowData>
            <volume>(0.8, 0.6, 0.6)</volume>
            <offset>(0,0,-0.3)</offset>
          </shadowData>
        </bodyGraphicData>
        <dessicatedBodyGraphicData>
          <texPath>Things/Nexomon/Voltaic/Dessicated_Voltaic</texPath>
          <drawSize>4.5</drawSize>
        </dessicatedBodyGraphicData>
      </li>
    </lifeStages>
  </PawnKindDef>
</Defs>